MANIFEST.in
README.rst
setup.py
mauticapi/__init__.py
mauticapi/mautic.py
mauticapi.egg-info/PKG-INFO
mauticapi.egg-info/SOURCES.txt
mauticapi.egg-info/dependency_links.txt
mauticapi.egg-info/not-zip-safe
mauticapi.egg-info/pbr.json
mauticapi.egg-info/requires.txt
mauticapi.egg-info/top_level.txt