Metadata-Version: 1.0
Name: mauticapi
Version: 0.2
Summary: An API for Mautic
Home-page: http://github.com/kleinq/mauticapi
Author: kleinq
Author-email: robert@robertwinder.com
License: MIT
Platform: UNKNOWN
